docudevs/__init__.py
docudevs/api/__init__.py
docudevs/api/configuration/__init__.py
docudevs/api/configuration/delete_configuration.py
docudevs/api/configuration/get_configuration.py
docudevs/api/configuration/list_configurations.py
docudevs/api/configuration/save_configuration.py
docudevs/api/document/__init__.py
docudevs/api/document/process_document.py
docudevs/api/document/upload_document.py
docudevs/api/document/upload_files.py
docudevs/api/document/upload_template.py
docudevs/api/job/__init__.py
docudevs/api/job/result.py
docudevs/api/job/status.py
docudevs/api/settings/__init__.py
docudevs/api/settings/settings.py
docudevs/api/template/__init__.py
docudevs/api/template/delete_template.py
docudevs/api/template/fill.py
docudevs/api/template/list_templates.py
docudevs/api/template/metadata.py
docudevs/client.py
docudevs/errors.py
docudevs/models/__init__.py
docudevs/models/document_template.py
docudevs/models/extraction_mode.py
docudevs/models/llm_type.py
docudevs/models/named_configuration.py
docudevs/models/ocr_type.py
docudevs/models/organization.py
docudevs/models/pdf_field.py
docudevs/models/processing_job.py
docudevs/models/settings.py
docudevs/models/template_fill_request.py
docudevs/models/upload_command.py
docudevs/models/upload_document_body.py
docudevs/models/upload_files_body.py
docudevs/models/upload_response.py
docudevs/models/upload_template_body.py
docudevs/py.typed
docudevs/types.py
docudevs-0.1.4.dist-info/METADATA
docudevs-0.1.4.dist-info/WHEEL
docudevs-0.1.4.dist-info/entry_points.txt
docudevs-0.1.4.dist-info/RECORD
