Metadata-Version: 2.3
Name: docudevs
Version: 0.1.4
Summary: A client library for accessing DocuDevs API
Author: pj@docudevs.ai
Requires-Python: >=3.9,<4.0
Classifier: Programming Language :: Python :: 3
Classifier: Programming Language :: Python :: 3.9
Classifier: Programming Language :: Python :: 3.10
Classifier: Programming Language :: Python :: 3.11
Classifier: Programming Language :: Python :: 3.12
Classifier: Programming Language :: Python :: 3.13
Requires-Dist: asyncio (>=3.4.3,<4.0.0)
Requires-Dist: attrs (>=21.3.0)
Requires-Dist: click (>=8.0.0,<9.0.0)
Requires-Dist: httpx (>=0.20.0,<0.28.1)
Requires-Dist: python-dateutil (>=2.8.0,<3.0.0)
